manual_testing/anthropic_native_test.py
manual_testing/anthropic_rest_test.py
manual_testing/cohere_native_test.py
manual_testing/gemini_google_test.py
manual_testing/gemini_rest_test.py
manual_testing/groq_native_test.py
manual_testing/groq_rest_test.py
manual_testing/openai_native_test.py
manual_testing/openai_rest_test.py
manual_testing/palm_rest_test.py
manual_testing/together_native_test.py
manual_testing/xai_openai_native_test.py
manual_testing/xai_rest_test.py
manual_testing/yaml_config.py
symposium/__init__.py
symposium/adapters/__init__.py
symposium/adapters/anth.py
symposium/adapters/coh_native.py
symposium/adapters/gem_native.py
symposium/adapters/gem_rest.py
symposium/adapters/grq_native.py
symposium/adapters/grq_rest.py
symposium/adapters/oai_native.py
symposium/adapters/oai_rest.py
symposium/adapters/plm_rest.py
symposium/adapters/tog_lma.py
symposium/adapters/xai_oai_native.py
symposium/adapters/xai_rest.py
symposium/connectors/__init__.py
symposium/connectors/anthropic_native.py
symposium/connectors/anthropic_rest.py
symposium/connectors/bedrock.py
symposium/connectors/brcloud.py
symposium/connectors/cohere_native.py
symposium/connectors/gemini_google.py
symposium/connectors/gemini_rest.py
symposium/connectors/govert.py
symposium/connectors/groq_native.py
symposium/connectors/groq_rest.py
symposium/connectors/hfhub_native.py
symposium/connectors/hugface.py
symposium/connectors/openai_native.py
symposium/connectors/openai_rest.py
symposium/connectors/palm_google.py
symposium/connectors/palm_rest.py
symposium/connectors/together_native.py
symposium/connectors/vertex.py
symposium/connectors/vertrest.py
symposium/connectors/xai_openai_native.py
symposium/connectors/xai_rest.py
symposium/recorders/__init__.py
symposium/recorders/githublog.py
symposium/templates/__init__.py
symposium/templates/four_hypotheses.py
symposium/templates/one_thread.py
symposium/templates/sentence.py
symposium/templates/three_branch.py
symposium/templates/two_branch.py
symposium-0.2.6.dist-info/LICENSE
symposium-0.2.6.dist-info/METADATA
symposium-0.2.6.dist-info/WHEEL
symposium-0.2.6.dist-info/top_level.txt
symposium-0.2.6.dist-info/RECORD
