Metadata-Version: 2.1
Name: symposium
Version: 0.2.6
Summary: Interaction of multiple language models
Author-email: Alexander Fedotov <alex.fedotov@aol.com>
Project-URL: Homepage, https://github.com/multilogue/symposium
Project-URL: Bug Tracker, https://github.com/multilogue/sumposium/issues
Keywords: symposium,conversations,ai
Classifier: Programming Language :: Python :: 3
Classifier: License :: OSI Approved :: MIT License
Classifier: Operating System :: OS Independent
Requires-Python: >=3.10
License-File: LICENSE
Requires-Dist: requests >=2.31.0
Requires-Dist: urllib3 >=1.26.16
Requires-Dist: grammateus >=0.0.10
Requires-Dist: PyYAML >=6.0.0
Requires-Dist: ruamel.yaml >=0.18.6
Provides-Extra: anthropic_native
Requires-Dist: anthropic >=0.26.0 ; extra == 'anthropic_native'
Provides-Extra: bedrock
Requires-Dist: boto3 >=1.28.57 ; extra == 'bedrock'
Provides-Extra: cohere
Requires-Dist: cohere >=5.5.7 ; extra == 'cohere'
Provides-Extra: gemini_google
Requires-Dist: google-generativeai >=0.5.4 ; extra == 'gemini_google'
Provides-Extra: github
Requires-Dist: PyGithub >=2.3.0 ; extra == 'github'
Provides-Extra: groq
Requires-Dist: groq >=0.6.0 ; extra == 'groq'
Provides-Extra: huggingface
Requires-Dist: huggingface-hub[inference] >=0.22.3 ; extra == 'huggingface'
Provides-Extra: openai_native
Requires-Dist: openai >=1.30.1 ; extra == 'openai_native'
Provides-Extra: vertex
Requires-Dist: google-cloud-aiplatform >=1.51.0 ; extra == 'vertex'
